LICENSE
MANIFEST.in
README.md
setup.py
./requirements.txt
bacs/__init__.py
bacs/classifier.py
bacs/evaluation.py
bacs/feature.py
bacs/reader.py
bacs/run.py
bacs/smoothing.py
bacs/writer.py
bacs/defmodel/readme
bacs/defmodel/saved_model.pb
bacs/defmodel/variables/variables.data-00000-of-00001
bacs/defmodel/variables/variables.index
brandeis_acs.egg-info/PKG-INFO
brandeis_acs.egg-info/SOURCES.txt
brandeis_acs.egg-info/dependency_links.txt
brandeis_acs.egg-info/entry_points.txt
brandeis_acs.egg-info/requires.txt
brandeis_acs.egg-info/top_level.txt