Metadata-Version: 2.1
Name: brandeis-acs
Version: 1.11
Summary: Brandeis Acoustic Classification & Segmentation tool
Home-page: https://github.com/brandeis-llc/acoustic-classification-segmentation
Author: Keigh Rim
Author-email: krim@brandeis.edu
License: MIT
Platform: UNKNOWN
License-File: LICENSE
